piczl/__init__.py
piczl/config/__init__.py
piczl/config/default_models.py
piczl/config/required_columns.py
piczl/config/training_config.py
piczl/core/__init__.py
piczl/core/estimator.py
piczl/core/trainer.py
piczl/demo_data/__init__.py
piczl/demo_data/__pycache__/__init__.cpython-39.pyc
piczl/demo_data/run/__init__.py
piczl/demo_data/run/demo_catalog.fits
piczl/demo_data/run/demo_images/aperture_images_LS10.npy
piczl/demo_data/run/demo_images/aperture_images_LS10_colours.npy
piczl/demo_data/run/demo_images/aperture_images_LS10_ivar.npy
piczl/demo_data/run/demo_images/aperture_images_WISE.npy
piczl/demo_data/run/demo_images/aperture_images_WISE_colours.npy
piczl/demo_data/run/demo_images/aperture_images_WISE_ivar.npy
piczl/demo_data/run/demo_images/aperture_images_WISE_residuals.npy
piczl/demo_data/run/demo_images/dered_griz_models.npy
piczl/demo_data/run/demo_images/dered_griz_residuals.npy
piczl/demo_data/run/demo_images/processed_dered_griz_colours.npy
piczl/demo_data/run/demo_images/processed_dered_griz_images.npy
piczl/demo_data/run/demo_images/psf_images.npy
piczl/demo_data/run/result/.gitkeep
piczl/demo_data/run/result/PICZL_predictions_demo_catalog.fits
piczl/demo_data/train/__init__.py
piczl/demo_data/train/demo_catalog.fits
piczl/demo_data/train/demo_images/aperture_images_LS10.npy
piczl/demo_data/train/demo_images/aperture_images_LS10_colours.npy
piczl/demo_data/train/demo_images/aperture_images_LS10_ivar.npy
piczl/demo_data/train/demo_images/aperture_images_WISE.npy
piczl/demo_data/train/demo_images/aperture_images_WISE_colours.npy
piczl/demo_data/train/demo_images/aperture_images_WISE_ivar.npy
piczl/demo_data/train/demo_images/aperture_images_WISE_residuals.npy
piczl/demo_data/train/demo_images/dered_griz_models.npy
piczl/demo_data/train/demo_images/dered_griz_residuals.npy
piczl/demo_data/train/demo_images/processed_dered_griz_colours.npy
piczl/demo_data/train/demo_images/processed_dered_griz_images.npy
piczl/demo_data/train/demo_images/psf_images.npy
piczl-0.1.4.dist-info/licenses/LICENSE
piczl-0.1.4.dist-info/METADATA
piczl-0.1.4.dist-info/WHEEL
piczl-0.1.4.dist-info/top_level.txt
piczl-0.1.4.dist-info/RECORD
