Metadata-Version: 2.4
Name: piczl
Version: 0.1.4
Summary: PICZL Photometric redshift estimation for AGN and galaxies
Author-email: William Roster <wroster@mpe.mpg.de>, Raphael Shirley <rshirley@mpe.mpg.de>
Requires-Python: >=3.6
License-File: LICENSE
Requires-Dist: tensorflow
Requires-Dist: tensorflow_probability
Requires-Dist: tf-keras
Requires-Dist: pytest
Requires-Dist: torch
Requires-Dist: pandas
Requires-Dist: matplotlib
Requires-Dist: scikit-learn
Requires-Dist: scipy
Requires-Dist: PyYAML
Requires-Dist: astropy
Requires-Dist: tqdm
Dynamic: license-file
